LICENSE
README.md
setup.cfg
setup.py
fastapi_ast_inference/__init__.py
fastapi_ast_inference/core.py
fastapi_ast_inference/decorator.py
fastapi_ast_inference/py.typed
fastapi_ast_inference/route.py
fastapi_ast_inference.egg-info/PKG-INFO
fastapi_ast_inference.egg-info/SOURCES.txt
fastapi_ast_inference.egg-info/dependency_links.txt
fastapi_ast_inference.egg-info/requires.txt
fastapi_ast_inference.egg-info/top_level.txt
tests/test_core.py
tests/test_decorator.py
tests/test_integration.py
tests/test_route.py